pyken/__init__.py
pyken/bojack.py
pyken/carpe.py
pyken/codex.py
pyken/diane.py
pyken/memento.py
pyken/mr_peanutbutter.py
pyken/princess_carolyn.py
pyken/todd.py
pyken/utilities_pyspark.py
pyken-0.8.2.dist-info/LICENSE
pyken-0.8.2.dist-info/METADATA
pyken-0.8.2.dist-info/WHEEL
pyken-0.8.2.dist-info/top_level.txt
pyken-0.8.2.dist-info/RECORD
