Metadata-Version: 2.1
Name: pyken
Version: 0.8.2
Summary: Scorecard development with Python
Home-page: https://github.com/Guilliu/pyken
Author: Guillermo Lizcano
Author-email: guille.lv.97@gmail.com
License: UNKNOWN
Keywords: python,rating,scoring,logistic-regression,scorecard,woe,credit-risk,autogrouping
Platform: UNKNOWN
Classifier: Programming Language :: Python :: 3
Classifier: License :: OSI Approved :: MIT License
Classifier: Operating System :: OS Independent
